{
  "port": 4000,
  "bundles": [
    "bundle-example-areas",
    "bundle-example-bugreport",
    "bundle-example-channels",
    "bundle-example-combat",
    "wraithsphere-commands",
    "bundle-example-crafting",
    "bundle-example-debug",
    "bundle-example-effects",
    "bundle-example-groups",
    "wraithsphere-input-events",
    "wraithsphere-lib",
    "bundle-example-npc-behaviors",
    "bundle-example-player-events",
    "bundle-example-quests",
    "bundle-example-telnet",
    "bundle-example-vendors",
    "bundle-example-websocket"
  ],
  "maxAccountNameLength": 20,
  "minAccountNameLength": 3,
  "maxPlayerNameLength": 20,
  "minPlayerNameLength": 3,
  "maxCharacters": 1,
  "allowMultiplay": false,
  "reportToAdmins": false,
  "startingRoom": "limbo:white",
  "moveCommand": "move",
  "skillLag": 2000,
  "defaultMaxPlayerInventory": 16,
  "maxIdleTime": 20
}